dform/__init__.py
dform/admin.py
dform/admin_urls.py
dform/fields.py
dform/forms.py
dform/models.py
dform/urls.py
dform/views.py
dform/migrations/0001_initial.py
dform/migrations/0002_survey_use_recaptcha.py
dform/migrations/0003_auto_20161026_1250.py
dform/migrations/0004_answergroup_ip_address.py
dform/migrations/0005_answergroup_ip_default.py
dform/migrations/0006_remove_survey_use_recaptcha.py
dform/migrations/0007_survey_show_title.py
dform/migrations/__init__.py
dform/static/dform/css/dform.css
dform/static/dform/js/pym.min.js
dform/templates/admin/dform/change_list.html
dform/templates/admin/dform/survey/change_list.html
dform/templates/dform/base.html
dform/templates/dform/edit_survey.html
dform/templates/dform/fields.html
dform/templates/dform/links_answers.html
dform/templates/dform/links_survey.html
dform/templates/dform/survey.html
dform/tests/__init__.py
dform/tests/test_dform.py
dform/tests/urls.py
django_dform-0.9.5.dist-info/DESCRIPTION.rst
django_dform-0.9.5.dist-info/METADATA
django_dform-0.9.5.dist-info/metadata.json
django_dform-0.9.5.dist-info/RECORD
django_dform-0.9.5.dist-info/top_level.txt
django_dform-0.9.5.dist-info/WHEEL
