Metadata-Version: 2.0
Name: django-dform
Version: 0.9.5
Summary: Django app for dynamic forms or surveys that can be injected in sites
Home-page: https://github.com/cltrudeau/django-dform
Author: Christopher Trudeau
Author-email: ctrudeau+pypi@arsensa.com
License: MIT
Keywords: django,form,survey
Platform: UNKNOWN
Classifier: Development Status :: 4 - Beta
Classifier: Environment :: Web Environment
Classifier: Intended Audience :: Developers
Classifier: License :: OSI Approved :: MIT License
Classifier: Operating System :: OS Independent
Classifier: Programming Language :: Python :: 2.7
Classifier: Programming Language :: Python :: 3.5
Classifier: Programming Language :: Python :: 3.6
Classifier: Topic :: Software Development :: Libraries :: Application Frameworks
Classifier: Topic :: Software Development :: Libraries :: Python Modules
Requires-Dist: Django (>=1.9)
Requires-Dist: django-awl (>=0.13)
Requires-Dist: wrench (>=0.9)
Requires-Dist: jsonfield (>=1.0.3)
